{
  "globals": {
    "abortNavigation": true,
    "actionSheetController": true,
    "addRouteMiddleware": true,
    "alertController": true,
    "callOnce": true,
    "cancelIdleCallback": true,
    "clearError": true,
    "clearNuxtData": true,
    "clearNuxtState": true,
    "computed": true,
    "createAnimation": true,
    "createError": true,
    "createGesture": true,
    "customRef": true,
    "defineAppConfig": true,
    "defineAsyncComponent": true,
    "defineComponent": true,
    "defineModel": true,
    "defineNuxtComponent": true,
    "defineNuxtLink": true,
    "defineNuxtPlugin": true,
    "defineNuxtRouteMiddleware": true,
    "defineOptions": true,
    "definePayloadPlugin": true,
    "definePayloadReducer": true,
    "definePayloadReviver": true,
    "defineSlots": true,
    "effect": true,
    "effectScope": true,
    "getAppManifest": true,
    "getCurrentInstance": true,
    "getCurrentScope": true,
    "getIonPageElement": true,
    "getPlatforms": true,
    "getRouteRules": true,
    "getTimeGivenProgression": true,
    "h": true,
    "hasInjectionContext": true,
    "inject": true,
    "injectHead": true,
    "ioniconsAccessibility": true,
    "ioniconsAccessibilityOutline": true,
    "ioniconsAccessibilitySharp": true,
    "ioniconsAdd": true,
    "ioniconsAddCircle": true,
    "ioniconsAddCircleOutline": true,
    "ioniconsAddCircleSharp": true,
    "ioniconsAddOutline": true,
    "ioniconsAddSharp": true,
    "ioniconsAirplane": true,
    "ioniconsAirplaneOutline": true,
    "ioniconsAirplaneSharp": true,
    "ioniconsAlarm": true,
    "ioniconsAlarmOutline": true,
    "ioniconsAlarmSharp": true,
    "ioniconsAlbums": true,
    "ioniconsAlbumsOutline": true,
    "ioniconsAlbumsSharp": true,
    "ioniconsAlert": true,
    "ioniconsAlertCircle": true,
    "ioniconsAlertCircleOutline": true,
    "ioniconsAlertCircleSharp": true,
    "ioniconsAlertOutline": true,
    "ioniconsAlertSharp": true,
    "ioniconsAmericanFootball": true,
    "ioniconsAmericanFootballOutline": true,
    "ioniconsAmericanFootballSharp": true,
    "ioniconsAnalytics": true,
    "ioniconsAnalyticsOutline": true,
    "ioniconsAnalyticsSharp": true,
    "ioniconsAperture": true,
    "ioniconsApertureOutline": true,
    "ioniconsApertureSharp": true,
    "ioniconsApps": true,
    "ioniconsAppsOutline": true,
    "ioniconsAppsSharp": true,
    "ioniconsArchive": true,
    "ioniconsArchiveOutline": true,
    "ioniconsArchiveSharp": true,
    "ioniconsArrowBack": true,
    "ioniconsArrowBackCircle": true,
    "ioniconsArrowBackCircleOutline": true,
    "ioniconsArrowBackCircleSharp": true,
    "ioniconsArrowBackOutline": true,
    "ioniconsArrowBackSharp": true,
    "ioniconsArrowDown": true,
    "ioniconsArrowDownCircle": true,
    "ioniconsArrowDownCircleOutline": true,
    "ioniconsArrowDownCircleSharp": true,
    "ioniconsArrowDownLeftBox": true,
    "ioniconsArrowDownLeftBoxOutline": true,
    "ioniconsArrowDownLeftBoxSharp": true,
    "ioniconsArrowDownOutline": true,
    "ioniconsArrowDownRightBox": true,
    "ioniconsArrowDownRightBoxOutline": true,
    "ioniconsArrowDownRightBoxSharp": true,
    "ioniconsArrowDownSharp": true,
    "ioniconsArrowForward": true,
    "ioniconsArrowForwardCircle": true,
    "ioniconsArrowForwardCircleOutline": true,
    "ioniconsArrowForwardCircleSharp": true,
    "ioniconsArrowForwardOutline": true,
    "ioniconsArrowForwardSharp": true,
    "ioniconsArrowRedo": true,
    "ioniconsArrowRedoCircle": true,
    "ioniconsArrowRedoCircleOutline": true,
    "ioniconsArrowRedoCircleSharp": true,
    "ioniconsArrowRedoOutline": true,
    "ioniconsArrowRedoSharp": true,
    "ioniconsArrowUndo": true,
    "ioniconsArrowUndoCircle": true,
    "ioniconsArrowUndoCircleOutline": true,
    "ioniconsArrowUndoCircleSharp": true,
    "ioniconsArrowUndoOutline": true,
    "ioniconsArrowUndoSharp": true,
    "ioniconsArrowUp": true,
    "ioniconsArrowUpCircle": true,
    "ioniconsArrowUpCircleOutline": true,
    "ioniconsArrowUpCircleSharp": true,
    "ioniconsArrowUpLeftBox": true,
    "ioniconsArrowUpLeftBoxOutline": true,
    "ioniconsArrowUpLeftBoxSharp": true,
    "ioniconsArrowUpOutline": true,
    "ioniconsArrowUpRightBox": true,
    "ioniconsArrowUpRightBoxOutline": true,
    "ioniconsArrowUpRightBoxSharp": true,
    "ioniconsArrowUpSharp": true,
    "ioniconsAt": true,
    "ioniconsAtCircle": true,
    "ioniconsAtCircleOutline": true,
    "ioniconsAtCircleSharp": true,
    "ioniconsAtOutline": true,
    "ioniconsAtSharp": true,
    "ioniconsAttach": true,
    "ioniconsAttachOutline": true,
    "ioniconsAttachSharp": true,
    "ioniconsBackspace": true,
    "ioniconsBackspaceOutline": true,
    "ioniconsBackspaceSharp": true,
    "ioniconsBag": true,
    "ioniconsBagAdd": true,
    "ioniconsBagAddOutline": true,
    "ioniconsBagAddSharp": true,
    "ioniconsBagCheck": true,
    "ioniconsBagCheckOutline": true,
    "ioniconsBagCheckSharp": true,
    "ioniconsBagHandle": true,
    "ioniconsBagHandleOutline": true,
    "ioniconsBagHandleSharp": true,
    "ioniconsBagOutline": true,
    "ioniconsBagRemove": true,
    "ioniconsBagRemoveOutline": true,
    "ioniconsBagRemoveSharp": true,
    "ioniconsBagSharp": true,
    "ioniconsBalloon": true,
    "ioniconsBalloonOutline": true,
    "ioniconsBalloonSharp": true,
    "ioniconsBan": true,
    "ioniconsBanOutline": true,
    "ioniconsBanSharp": true,
    "ioniconsBandage": true,
    "ioniconsBandageOutline": true,
    "ioniconsBandageSharp": true,
    "ioniconsBarChart": true,
    "ioniconsBarChartOutline": true,
    "ioniconsBarChartSharp": true,
    "ioniconsBarbell": true,
    "ioniconsBarbellOutline": true,
    "ioniconsBarbellSharp": true,
    "ioniconsBarcode": true,
    "ioniconsBarcodeOutline": true,
    "ioniconsBarcodeSharp": true,
    "ioniconsBaseball": true,
    "ioniconsBaseballOutline": true,
    "ioniconsBaseballSharp": true,
    "ioniconsBasket": true,
    "ioniconsBasketOutline": true,
    "ioniconsBasketSharp": true,
    "ioniconsBasketball": true,
    "ioniconsBasketballOutline": true,
    "ioniconsBasketballSharp": true,
    "ioniconsBatteryCharging": true,
    "ioniconsBatteryChargingOutline": true,
    "ioniconsBatteryChargingSharp": true,
    "ioniconsBatteryDead": true,
    "ioniconsBatteryDeadOutline": true,
    "ioniconsBatteryDeadSharp": true,
    "ioniconsBatteryFull": true,
    "ioniconsBatteryFullOutline": true,
    "ioniconsBatteryFullSharp": true,
    "ioniconsBatteryHalf": true,
    "ioniconsBatteryHalfOutline": true,
    "ioniconsBatteryHalfSharp": true,
    "ioniconsBeaker": true,
    "ioniconsBeakerOutline": true,
    "ioniconsBeakerSharp": true,
    "ioniconsBed": true,
    "ioniconsBedOutline": true,
    "ioniconsBedSharp": true,
    "ioniconsBeer": true,
    "ioniconsBeerOutline": true,
    "ioniconsBeerSharp": true,
    "ioniconsBicycle": true,
    "ioniconsBicycleOutline": true,
    "ioniconsBicycleSharp": true,
    "ioniconsBinoculars": true,
    "ioniconsBinocularsOutline": true,
    "ioniconsBinocularsSharp": true,
    "ioniconsBluetooth": true,
    "ioniconsBluetoothOutline": true,
    "ioniconsBluetoothSharp": true,
    "ioniconsBoat": true,
    "ioniconsBoatOutline": true,
    "ioniconsBoatSharp": true,
    "ioniconsBody": true,
    "ioniconsBodyOutline": true,
    "ioniconsBodySharp": true,
    "ioniconsBonfire": true,
    "ioniconsBonfireOutline": true,
    "ioniconsBonfireSharp": true,
    "ioniconsBook": true,
    "ioniconsBookOutline": true,
    "ioniconsBookSharp": true,
    "ioniconsBookmark": true,
    "ioniconsBookmarkOutline": true,
    "ioniconsBookmarkSharp": true,
    "ioniconsBookmarks": true,
    "ioniconsBookmarksOutline": true,
    "ioniconsBookmarksSharp": true,
    "ioniconsBowlingBall": true,
    "ioniconsBowlingBallOutline": true,
    "ioniconsBowlingBallSharp": true,
    "ioniconsBriefcase": true,
    "ioniconsBriefcaseOutline": true,
    "ioniconsBriefcaseSharp": true,
    "ioniconsBrowsers": true,
    "ioniconsBrowsersOutline": true,
    "ioniconsBrowsersSharp": true,
    "ioniconsBrush": true,
    "ioniconsBrushOutline": true,
    "ioniconsBrushSharp": true,
    "ioniconsBug": true,
    "ioniconsBugOutline": true,
    "ioniconsBugSharp": true,
    "ioniconsBuild": true,
    "ioniconsBuildOutline": true,
    "ioniconsBuildSharp": true,
    "ioniconsBulb": true,
    "ioniconsBulbOutline": true,
    "ioniconsBulbSharp": true,
    "ioniconsBus": true,
    "ioniconsBusOutline": true,
    "ioniconsBusSharp": true,
    "ioniconsBusiness": true,
    "ioniconsBusinessOutline": true,
    "ioniconsBusinessSharp": true,
    "ioniconsCafe": true,
    "ioniconsCafeOutline": true,
    "ioniconsCafeSharp": true,
    "ioniconsCalculator": true,
    "ioniconsCalculatorOutline": true,
    "ioniconsCalculatorSharp": true,
    "ioniconsCalendar": true,
    "ioniconsCalendarClear": true,
    "ioniconsCalendarClearOutline": true,
    "ioniconsCalendarClearSharp": true,
    "ioniconsCalendarNumber": true,
    "ioniconsCalendarNumberOutline": true,
    "ioniconsCalendarNumberSharp": true,
    "ioniconsCalendarOutline": true,
    "ioniconsCalendarSharp": true,
    "ioniconsCall": true,
    "ioniconsCallOutline": true,
    "ioniconsCallSharp": true,
    "ioniconsCamera": true,
    "ioniconsCameraOutline": true,
    "ioniconsCameraReverse": true,
    "ioniconsCameraReverseOutline": true,
    "ioniconsCameraReverseSharp": true,
    "ioniconsCameraSharp": true,
    "ioniconsCar": true,
    "ioniconsCarOutline": true,
    "ioniconsCarSharp": true,
    "ioniconsCarSport": true,
    "ioniconsCarSportOutline": true,
    "ioniconsCarSportSharp": true,
    "ioniconsCard": true,
    "ioniconsCardOutline": true,
    "ioniconsCardSharp": true,
    "ioniconsCaretBack": true,
    "ioniconsCaretBackCircle": true,
    "ioniconsCaretBackCircleOutline": true,
    "ioniconsCaretBackCircleSharp": true,
    "ioniconsCaretBackOutline": true,
    "ioniconsCaretBackSharp": true,
    "ioniconsCaretDown": true,
    "ioniconsCaretDownCircle": true,
    "ioniconsCaretDownCircleOutline": true,
    "ioniconsCaretDownCircleSharp": true,
    "ioniconsCaretDownOutline": true,
    "ioniconsCaretDownSharp": true,
    "ioniconsCaretForward": true,
    "ioniconsCaretForwardCircle": true,
    "ioniconsCaretForwardCircleOutline": true,
    "ioniconsCaretForwardCircleSharp": true,
    "ioniconsCaretForwardOutline": true,
    "ioniconsCaretForwardSharp": true,
    "ioniconsCaretUp": true,
    "ioniconsCaretUpCircle": true,
    "ioniconsCaretUpCircleOutline": true,
    "ioniconsCaretUpCircleSharp": true,
    "ioniconsCaretUpOutline": true,
    "ioniconsCaretUpSharp": true,
    "ioniconsCart": true,
    "ioniconsCartOutline": true,
    "ioniconsCartSharp": true,
    "ioniconsCash": true,
    "ioniconsCashOutline": true,
    "ioniconsCashSharp": true,
    "ioniconsCellular": true,
    "ioniconsCellularOutline": true,
    "ioniconsCellularSharp": true,
    "ioniconsChatbox": true,
    "ioniconsChatboxEllipses": true,
    "ioniconsChatboxEllipsesOutline": true,
    "ioniconsChatboxEllipsesSharp": true,
    "ioniconsChatboxOutline": true,
    "ioniconsChatboxSharp": true,
    "ioniconsChatbubble": true,
    "ioniconsChatbubbleEllipses": true,
    "ioniconsChatbubbleEllipsesOutline": true,
    "ioniconsChatbubbleEllipsesSharp": true,
    "ioniconsChatbubbleOutline": true,
    "ioniconsChatbubbleSharp": true,
    "ioniconsChatbubbles": true,
    "ioniconsChatbubblesOutline": true,
    "ioniconsChatbubblesSharp": true,
    "ioniconsCheckbox": true,
    "ioniconsCheckboxOutline": true,
    "ioniconsCheckboxSharp": true,
    "ioniconsCheckmark": true,
    "ioniconsCheckmarkCircle": true,
    "ioniconsCheckmarkCircleOutline": true,
    "ioniconsCheckmarkCircleSharp": true,
    "ioniconsCheckmarkDone": true,
    "ioniconsCheckmarkDoneCircle": true,
    "ioniconsCheckmarkDoneCircleOutline": true,
    "ioniconsCheckmarkDoneCircleSharp": true,
    "ioniconsCheckmarkDoneOutline": true,
    "ioniconsCheckmarkDoneSharp": true,
    "ioniconsCheckmarkOutline": true,
    "ioniconsCheckmarkSharp": true,
    "ioniconsChevronBack": true,
    "ioniconsChevronBackCircle": true,
    "ioniconsChevronBackCircleOutline": true,
    "ioniconsChevronBackCircleSharp": true,
    "ioniconsChevronBackOutline": true,
    "ioniconsChevronBackSharp": true,
    "ioniconsChevronCollapse": true,
    "ioniconsChevronCollapseOutline": true,
    "ioniconsChevronCollapseSharp": true,
    "ioniconsChevronDown": true,
    "ioniconsChevronDownCircle": true,
    "ioniconsChevronDownCircleOutline": true,
    "ioniconsChevronDownCircleSharp": true,
    "ioniconsChevronDownOutline": true,
    "ioniconsChevronDownSharp": true,
    "ioniconsChevronExpand": true,
    "ioniconsChevronExpandOutline": true,
    "ioniconsChevronExpandSharp": true,
    "ioniconsChevronForward": true,
    "ioniconsChevronForwardCircle": true,
    "ioniconsChevronForwardCircleOutline": true,
    "ioniconsChevronForwardCircleSharp": true,
    "ioniconsChevronForwardOutline": true,
    "ioniconsChevronForwardSharp": true,
    "ioniconsChevronUp": true,
    "ioniconsChevronUpCircle": true,
    "ioniconsChevronUpCircleOutline": true,
    "ioniconsChevronUpCircleSharp": true,
    "ioniconsChevronUpOutline": true,
    "ioniconsChevronUpSharp": true,
    "ioniconsClipboard": true,
    "ioniconsClipboardOutline": true,
    "ioniconsClipboardSharp": true,
    "ioniconsClose": true,
    "ioniconsCloseCircle": true,
    "ioniconsCloseCircleOutline": true,
    "ioniconsCloseCircleSharp": true,
    "ioniconsCloseOutline": true,
    "ioniconsCloseSharp": true,
    "ioniconsCloud": true,
    "ioniconsCloudCircle": true,
    "ioniconsCloudCircleOutline": true,
    "ioniconsCloudCircleSharp": true,
    "ioniconsCloudDone": true,
    "ioniconsCloudDoneOutline": true,
    "ioniconsCloudDoneSharp": true,
    "ioniconsCloudDownload": true,
    "ioniconsCloudDownloadOutline": true,
    "ioniconsCloudDownloadSharp": true,
    "ioniconsCloudOffline": true,
    "ioniconsCloudOfflineOutline": true,
    "ioniconsCloudOfflineSharp": true,
    "ioniconsCloudOutline": true,
    "ioniconsCloudSharp": true,
    "ioniconsCloudUpload": true,
    "ioniconsCloudUploadOutline": true,
    "ioniconsCloudUploadSharp": true,
    "ioniconsCloudy": true,
    "ioniconsCloudyNight": true,
    "ioniconsCloudyNightOutline": true,
    "ioniconsCloudyNightSharp": true,
    "ioniconsCloudyOutline": true,
    "ioniconsCloudySharp": true,
    "ioniconsCode": true,
    "ioniconsCodeDownload": true,
    "ioniconsCodeDownloadOutline": true,
    "ioniconsCodeDownloadSharp": true,
    "ioniconsCodeOutline": true,
    "ioniconsCodeSharp": true,
    "ioniconsCodeSlash": true,
    "ioniconsCodeSlashOutline": true,
    "ioniconsCodeSlashSharp": true,
    "ioniconsCodeWorking": true,
    "ioniconsCodeWorkingOutline": true,
    "ioniconsCodeWorkingSharp": true,
    "ioniconsCog": true,
    "ioniconsCogOutline": true,
    "ioniconsCogSharp": true,
    "ioniconsColorFill": true,
    "ioniconsColorFillOutline": true,
    "ioniconsColorFillSharp": true,
    "ioniconsColorFilter": true,
    "ioniconsColorFilterOutline": true,
    "ioniconsColorFilterSharp": true,
    "ioniconsColorPalette": true,
    "ioniconsColorPaletteOutline": true,
    "ioniconsColorPaletteSharp": true,
    "ioniconsColorWand": true,
    "ioniconsColorWandOutline": true,
    "ioniconsColorWandSharp": true,
    "ioniconsCompass": true,
    "ioniconsCompassOutline": true,
    "ioniconsCompassSharp": true,
    "ioniconsConstruct": true,
    "ioniconsConstructOutline": true,
    "ioniconsConstructSharp": true,
    "ioniconsContract": true,
    "ioniconsContractOutline": true,
    "ioniconsContractSharp": true,
    "ioniconsContrast": true,
    "ioniconsContrastOutline": true,
    "ioniconsContrastSharp": true,
    "ioniconsCopy": true,
    "ioniconsCopyOutline": true,
    "ioniconsCopySharp": true,
    "ioniconsCreate": true,
    "ioniconsCreateOutline": true,
    "ioniconsCreateSharp": true,
    "ioniconsCrop": true,
    "ioniconsCropOutline": true,
    "ioniconsCropSharp": true,
    "ioniconsCube": true,
    "ioniconsCubeOutline": true,
    "ioniconsCubeSharp": true,
    "ioniconsCut": true,
    "ioniconsCutOutline": true,
    "ioniconsCutSharp": true,
    "ioniconsDesktop": true,
    "ioniconsDesktopOutline": true,
    "ioniconsDesktopSharp": true,
    "ioniconsDiamond": true,
    "ioniconsDiamondOutline": true,
    "ioniconsDiamondSharp": true,
    "ioniconsDice": true,
    "ioniconsDiceOutline": true,
    "ioniconsDiceSharp": true,
    "ioniconsDisc": true,
    "ioniconsDiscOutline": true,
    "ioniconsDiscSharp": true,
    "ioniconsDocument": true,
    "ioniconsDocumentAttach": true,
    "ioniconsDocumentAttachOutline": true,
    "ioniconsDocumentAttachSharp": true,
    "ioniconsDocumentLock": true,
    "ioniconsDocumentLockOutline": true,
    "ioniconsDocumentLockSharp": true,
    "ioniconsDocumentOutline": true,
    "ioniconsDocumentSharp": true,
    "ioniconsDocumentText": true,
    "ioniconsDocumentTextOutline": true,
    "ioniconsDocumentTextSharp": true,
    "ioniconsDocuments": true,
    "ioniconsDocumentsOutline": true,
    "ioniconsDocumentsSharp": true,
    "ioniconsDownload": true,
    "ioniconsDownloadOutline": true,
    "ioniconsDownloadSharp": true,
    "ioniconsDuplicate": true,
    "ioniconsDuplicateOutline": true,
    "ioniconsDuplicateSharp": true,
    "ioniconsEar": true,
    "ioniconsEarOutline": true,
    "ioniconsEarSharp": true,
    "ioniconsEarth": true,
    "ioniconsEarthOutline": true,
    "ioniconsEarthSharp": true,
    "ioniconsEasel": true,
    "ioniconsEaselOutline": true,
    "ioniconsEaselSharp": true,
    "ioniconsEgg": true,
    "ioniconsEggOutline": true,
    "ioniconsEggSharp": true,
    "ioniconsEllipse": true,
    "ioniconsEllipseOutline": true,
    "ioniconsEllipseSharp": true,
    "ioniconsEllipsisHorizontal": true,
    "ioniconsEllipsisHorizontalCircle": true,
    "ioniconsEllipsisHorizontalCircleOutline": true,
    "ioniconsEllipsisHorizontalCircleSharp": true,
    "ioniconsEllipsisHorizontalOutline": true,
    "ioniconsEllipsisHorizontalSharp": true,
    "ioniconsEllipsisVertical": true,
    "ioniconsEllipsisVerticalCircle": true,
    "ioniconsEllipsisVerticalCircleOutline": true,
    "ioniconsEllipsisVerticalCircleSharp": true,
    "ioniconsEllipsisVerticalOutline": true,
    "ioniconsEllipsisVerticalSharp": true,
    "ioniconsEnter": true,
    "ioniconsEnterOutline": true,
    "ioniconsEnterSharp": true,
    "ioniconsExit": true,
    "ioniconsExitOutline": true,
    "ioniconsExitSharp": true,
    "ioniconsExpand": true,
    "ioniconsExpandOutline": true,
    "ioniconsExpandSharp": true,
    "ioniconsExtensionPuzzle": true,
    "ioniconsExtensionPuzzleOutline": true,
    "ioniconsExtensionPuzzleSharp": true,
    "ioniconsEye": true,
    "ioniconsEyeOff": true,
    "ioniconsEyeOffOutline": true,
    "ioniconsEyeOffSharp": true,
    "ioniconsEyeOutline": true,
    "ioniconsEyeSharp": true,
    "ioniconsEyedrop": true,
    "ioniconsEyedropOutline": true,
    "ioniconsEyedropSharp": true,
    "ioniconsFastFood": true,
    "ioniconsFastFoodOutline": true,
    "ioniconsFastFoodSharp": true,
    "ioniconsFemale": true,
    "ioniconsFemaleOutline": true,
    "ioniconsFemaleSharp": true,
    "ioniconsFileTray": true,
    "ioniconsFileTrayFull": true,
    "ioniconsFileTrayFullOutline": true,
    "ioniconsFileTrayFullSharp": true,
    "ioniconsFileTrayOutline": true,
    "ioniconsFileTraySharp": true,
    "ioniconsFileTrayStacked": true,
    "ioniconsFileTrayStackedOutline": true,
    "ioniconsFileTrayStackedSharp": true,
    "ioniconsFilm": true,
    "ioniconsFilmOutline": true,
    "ioniconsFilmSharp": true,
    "ioniconsFilter": true,
    "ioniconsFilterCircle": true,
    "ioniconsFilterCircleOutline": true,
    "ioniconsFilterCircleSharp": true,
    "ioniconsFilterOutline": true,
    "ioniconsFilterSharp": true,
    "ioniconsFingerPrint": true,
    "ioniconsFingerPrintOutline": true,
    "ioniconsFingerPrintSharp": true,
    "ioniconsFish": true,
    "ioniconsFishOutline": true,
    "ioniconsFishSharp": true,
    "ioniconsFitness": true,
    "ioniconsFitnessOutline": true,
    "ioniconsFitnessSharp": true,
    "ioniconsFlag": true,
    "ioniconsFlagOutline": true,
    "ioniconsFlagSharp": true,
    "ioniconsFlame": true,
    "ioniconsFlameOutline": true,
    "ioniconsFlameSharp": true,
    "ioniconsFlash": true,
    "ioniconsFlashOff": true,
    "ioniconsFlashOffOutline": true,
    "ioniconsFlashOffSharp": true,
    "ioniconsFlashOutline": true,
    "ioniconsFlashSharp": true,
    "ioniconsFlashlight": true,
    "ioniconsFlashlightOutline": true,
    "ioniconsFlashlightSharp": true,
    "ioniconsFlask": true,
    "ioniconsFlaskOutline": true,
    "ioniconsFlaskSharp": true,
    "ioniconsFlower": true,
    "ioniconsFlowerOutline": true,
    "ioniconsFlowerSharp": true,
    "ioniconsFolder": true,
    "ioniconsFolderOpen": true,
    "ioniconsFolderOpenOutline": true,
    "ioniconsFolderOpenSharp": true,
    "ioniconsFolderOutline": true,
    "ioniconsFolderSharp": true,
    "ioniconsFootball": true,
    "ioniconsFootballOutline": true,
    "ioniconsFootballSharp": true,
    "ioniconsFootsteps": true,
    "ioniconsFootstepsOutline": true,
    "ioniconsFootstepsSharp": true,
    "ioniconsFunnel": true,
    "ioniconsFunnelOutline": true,
    "ioniconsFunnelSharp": true,
    "ioniconsGameController": true,
    "ioniconsGameControllerOutline": true,
    "ioniconsGameControllerSharp": true,
    "ioniconsGift": true,
    "ioniconsGiftOutline": true,
    "ioniconsGiftSharp": true,
    "ioniconsGitBranch": true,
    "ioniconsGitBranchOutline": true,
    "ioniconsGitBranchSharp": true,
    "ioniconsGitCommit": true,
    "ioniconsGitCommitOutline": true,
    "ioniconsGitCommitSharp": true,
    "ioniconsGitCompare": true,
    "ioniconsGitCompareOutline": true,
    "ioniconsGitCompareSharp": true,
    "ioniconsGitMerge": true,
    "ioniconsGitMergeOutline": true,
    "ioniconsGitMergeSharp": true,
    "ioniconsGitNetwork": true,
    "ioniconsGitNetworkOutline": true,
    "ioniconsGitNetworkSharp": true,
    "ioniconsGitPullRequest": true,
    "ioniconsGitPullRequestOutline": true,
    "ioniconsGitPullRequestSharp": true,
    "ioniconsGlasses": true,
    "ioniconsGlassesOutline": true,
    "ioniconsGlassesSharp": true,
    "ioniconsGlobe": true,
    "ioniconsGlobeOutline": true,
    "ioniconsGlobeSharp": true,
    "ioniconsGolf": true,
    "ioniconsGolfOutline": true,
    "ioniconsGolfSharp": true,
    "ioniconsGrid": true,
    "ioniconsGridOutline": true,
    "ioniconsGridSharp": true,
    "ioniconsHammer": true,
    "ioniconsHammerOutline": true,
    "ioniconsHammerSharp": true,
    "ioniconsHandLeft": true,
    "ioniconsHandLeftOutline": true,
    "ioniconsHandLeftSharp": true,
    "ioniconsHandRight": true,
    "ioniconsHandRightOutline": true,
    "ioniconsHandRightSharp": true,
    "ioniconsHappy": true,
    "ioniconsHappyOutline": true,
    "ioniconsHappySharp": true,
    "ioniconsHardwareChip": true,
    "ioniconsHardwareChipOutline": true,
    "ioniconsHardwareChipSharp": true,
    "ioniconsHeadset": true,
    "ioniconsHeadsetOutline": true,
    "ioniconsHeadsetSharp": true,
    "ioniconsHeart": true,
    "ioniconsHeartCircle": true,
    "ioniconsHeartCircleOutline": true,
    "ioniconsHeartCircleSharp": true,
    "ioniconsHeartDislike": true,
    "ioniconsHeartDislikeCircle": true,
    "ioniconsHeartDislikeCircleOutline": true,
    "ioniconsHeartDislikeCircleSharp": true,
    "ioniconsHeartDislikeOutline": true,
    "ioniconsHeartDislikeSharp": true,
    "ioniconsHeartHalf": true,
    "ioniconsHeartHalfOutline": true,
    "ioniconsHeartHalfSharp": true,
    "ioniconsHeartOutline": true,
    "ioniconsHeartSharp": true,
    "ioniconsHelp": true,
    "ioniconsHelpBuoy": true,
    "ioniconsHelpBuoyOutline": true,
    "ioniconsHelpBuoySharp": true,
    "ioniconsHelpCircle": true,
    "ioniconsHelpCircleOutline": true,
    "ioniconsHelpCircleSharp": true,
    "ioniconsHelpOutline": true,
    "ioniconsHelpSharp": true,
    "ioniconsHome": true,
    "ioniconsHomeOutline": true,
    "ioniconsHomeSharp": true,
    "ioniconsHourglass": true,
    "ioniconsHourglassOutline": true,
    "ioniconsHourglassSharp": true,
    "ioniconsIceCream": true,
    "ioniconsIceCreamOutline": true,
    "ioniconsIceCreamSharp": true,
    "ioniconsIdCard": true,
    "ioniconsIdCardOutline": true,
    "ioniconsIdCardSharp": true,
    "ioniconsImage": true,
    "ioniconsImageOutline": true,
    "ioniconsImageSharp": true,
    "ioniconsImages": true,
    "ioniconsImagesOutline": true,
    "ioniconsImagesSharp": true,
    "ioniconsInfinite": true,
    "ioniconsInfiniteOutline": true,
    "ioniconsInfiniteSharp": true,
    "ioniconsInformation": true,
    "ioniconsInformationCircle": true,
    "ioniconsInformationCircleOutline": true,
    "ioniconsInformationCircleSharp": true,
    "ioniconsInformationOutline": true,
    "ioniconsInformationSharp": true,
    "ioniconsInvertMode": true,
    "ioniconsInvertModeOutline": true,
    "ioniconsInvertModeSharp": true,
    "ioniconsJournal": true,
    "ioniconsJournalOutline": true,
    "ioniconsJournalSharp": true,
    "ioniconsKey": true,
    "ioniconsKeyOutline": true,
    "ioniconsKeySharp": true,
    "ioniconsKeypad": true,
    "ioniconsKeypadOutline": true,
    "ioniconsKeypadSharp": true,
    "ioniconsLanguage": true,
    "ioniconsLanguageOutline": true,
    "ioniconsLanguageSharp": true,
    "ioniconsLaptop": true,
    "ioniconsLaptopOutline": true,
    "ioniconsLaptopSharp": true,
    "ioniconsLayers": true,
    "ioniconsLayersOutline": true,
    "ioniconsLayersSharp": true,
    "ioniconsLeaf": true,
    "ioniconsLeafOutline": true,
    "ioniconsLeafSharp": true,
    "ioniconsLibrary": true,
    "ioniconsLibraryOutline": true,
    "ioniconsLibrarySharp": true,
    "ioniconsLink": true,
    "ioniconsLinkOutline": true,
    "ioniconsLinkSharp": true,
    "ioniconsList": true,
    "ioniconsListCircle": true,
    "ioniconsListCircleOutline": true,
    "ioniconsListCircleSharp": true,
    "ioniconsListOutline": true,
    "ioniconsListSharp": true,
    "ioniconsLocate": true,
    "ioniconsLocateOutline": true,
    "ioniconsLocateSharp": true,
    "ioniconsLocation": true,
    "ioniconsLocationOutline": true,
    "ioniconsLocationSharp": true,
    "ioniconsLockClosed": true,
    "ioniconsLockClosedOutline": true,
    "ioniconsLockClosedSharp": true,
    "ioniconsLockOpen": true,
    "ioniconsLockOpenOutline": true,
    "ioniconsLockOpenSharp": true,
    "ioniconsLogIn": true,
    "ioniconsLogInOutline": true,
    "ioniconsLogInSharp": true,
    "ioniconsLogOut": true,
    "ioniconsLogOutOutline": true,
    "ioniconsLogOutSharp": true,
    "ioniconsLogoAlipay": true,
    "ioniconsLogoAmazon": true,
    "ioniconsLogoAmplify": true,
    "ioniconsLogoAndroid": true,
    "ioniconsLogoAngular": true,
    "ioniconsLogoAppflow": true,
    "ioniconsLogoApple": true,
    "ioniconsLogoAppleAppstore": true,
    "ioniconsLogoAppleAr": true,
    "ioniconsLogoBehance": true,
    "ioniconsLogoBitbucket": true,
    "ioniconsLogoBitcoin": true,
    "ioniconsLogoBuffer": true,
    "ioniconsLogoCapacitor": true,
    "ioniconsLogoChrome": true,
    "ioniconsLogoClosedCaptioning": true,
    "ioniconsLogoCodepen": true,
    "ioniconsLogoCss3": true,
    "ioniconsLogoDesignernews": true,
    "ioniconsLogoDeviantart": true,
    "ioniconsLogoDiscord": true,
    "ioniconsLogoDocker": true,
    "ioniconsLogoDribbble": true,
    "ioniconsLogoDropbox": true,
    "ioniconsLogoEdge": true,
    "ioniconsLogoElectron": true,
    "ioniconsLogoEuro": true,
    "ioniconsLogoFacebook": true,
    "ioniconsLogoFigma": true,
    "ioniconsLogoFirebase": true,
    "ioniconsLogoFirefox": true,
    "ioniconsLogoFlickr": true,
    "ioniconsLogoFoursquare": true,
    "ioniconsLogoGithub": true,
    "ioniconsLogoGitlab": true,
    "ioniconsLogoGoogle": true,
    "ioniconsLogoGooglePlaystore": true,
    "ioniconsLogoHackernews": true,
    "ioniconsLogoHtml5": true,
    "ioniconsLogoInstagram": true,
    "ioniconsLogoIonic": true,
    "ioniconsLogoIonitron": true,
    "ioniconsLogoJavascript": true,
    "ioniconsLogoLaravel": true,
    "ioniconsLogoLinkedin": true,
    "ioniconsLogoMarkdown": true,
    "ioniconsLogoMastodon": true,
    "ioniconsLogoMedium": true,
    "ioniconsLogoMicrosoft": true,
    "ioniconsLogoNoSmoking": true,
    "ioniconsLogoNodejs": true,
    "ioniconsLogoNpm": true,
    "ioniconsLogoOctocat": true,
    "ioniconsLogoPaypal": true,
    "ioniconsLogoPinterest": true,
    "ioniconsLogoPlaystation": true,
    "ioniconsLogoPwa": true,
    "ioniconsLogoPython": true,
    "ioniconsLogoReact": true,
    "ioniconsLogoReddit": true,
    "ioniconsLogoRss": true,
    "ioniconsLogoSass": true,
    "ioniconsLogoSkype": true,
    "ioniconsLogoSlack": true,
    "ioniconsLogoSnapchat": true,
    "ioniconsLogoSoundcloud": true,
    "ioniconsLogoStackoverflow": true,
    "ioniconsLogoSteam": true,
    "ioniconsLogoStencil": true,
    "ioniconsLogoTableau": true,
    "ioniconsLogoTiktok": true,
    "ioniconsLogoTrapeze": true,
    "ioniconsLogoTumblr": true,
    "ioniconsLogoTux": true,
    "ioniconsLogoTwitch": true,
    "ioniconsLogoTwitter": true,
    "ioniconsLogoUsd": true,
    "ioniconsLogoVenmo": true,
    "ioniconsLogoVercel": true,
    "ioniconsLogoVimeo": true,
    "ioniconsLogoVk": true,
    "ioniconsLogoVue": true,
    "ioniconsLogoWebComponent": true,
    "ioniconsLogoWechat": true,
    "ioniconsLogoWhatsapp": true,
    "ioniconsLogoWindows": true,
    "ioniconsLogoWordpress": true,
    "ioniconsLogoX": true,
    "ioniconsLogoXbox": true,
    "ioniconsLogoXing": true,
    "ioniconsLogoYahoo": true,
    "ioniconsLogoYen": true,
    "ioniconsLogoYoutube": true,
    "ioniconsMagnet": true,
    "ioniconsMagnetOutline": true,
    "ioniconsMagnetSharp": true,
    "ioniconsMail": true,
    "ioniconsMailOpen": true,
    "ioniconsMailOpenOutline": true,
    "ioniconsMailOpenSharp": true,
    "ioniconsMailOutline": true,
    "ioniconsMailSharp": true,
    "ioniconsMailUnread": true,
    "ioniconsMailUnreadOutline": true,
    "ioniconsMailUnreadSharp": true,
    "ioniconsMale": true,
    "ioniconsMaleFemale": true,
    "ioniconsMaleFemaleOutline": true,
    "ioniconsMaleFemaleSharp": true,
    "ioniconsMaleOutline": true,
    "ioniconsMaleSharp": true,
    "ioniconsMan": true,
    "ioniconsManOutline": true,
    "ioniconsManSharp": true,
    "ioniconsMap": true,
    "ioniconsMapOutline": true,
    "ioniconsMapSharp": true,
    "ioniconsMedal": true,
    "ioniconsMedalOutline": true,
    "ioniconsMedalSharp": true,
    "ioniconsMedical": true,
    "ioniconsMedicalOutline": true,
    "ioniconsMedicalSharp": true,
    "ioniconsMedkit": true,
    "ioniconsMedkitOutline": true,
    "ioniconsMedkitSharp": true,
    "ioniconsMegaphone": true,
    "ioniconsMegaphoneOutline": true,
    "ioniconsMegaphoneSharp": true,
    "ioniconsMenu": true,
    "ioniconsMenuOutline": true,
    "ioniconsMenuSharp": true,
    "ioniconsMic": true,
    "ioniconsMicCircle": true,
    "ioniconsMicCircleOutline": true,
    "ioniconsMicCircleSharp": true,
    "ioniconsMicOff": true,
    "ioniconsMicOffCircle": true,
    "ioniconsMicOffCircleOutline": true,
    "ioniconsMicOffCircleSharp": true,
    "ioniconsMicOffOutline": true,
    "ioniconsMicOffSharp": true,
    "ioniconsMicOutline": true,
    "ioniconsMicSharp": true,
    "ioniconsMoon": true,
    "ioniconsMoonOutline": true,
    "ioniconsMoonSharp": true,
    "ioniconsMove": true,
    "ioniconsMoveOutline": true,
    "ioniconsMoveSharp": true,
    "ioniconsMusicalNote": true,
    "ioniconsMusicalNoteOutline": true,
    "ioniconsMusicalNoteSharp": true,
    "ioniconsMusicalNotes": true,
    "ioniconsMusicalNotesOutline": true,
    "ioniconsMusicalNotesSharp": true,
    "ioniconsNavigate": true,
    "ioniconsNavigateCircle": true,
    "ioniconsNavigateCircleOutline": true,
    "ioniconsNavigateCircleSharp": true,
    "ioniconsNavigateOutline": true,
    "ioniconsNavigateSharp": true,
    "ioniconsNewspaper": true,
    "ioniconsNewspaperOutline": true,
    "ioniconsNewspaperSharp": true,
    "ioniconsNotifications": true,
    "ioniconsNotificationsCircle": true,
    "ioniconsNotificationsCircleOutline": true,
    "ioniconsNotificationsCircleSharp": true,
    "ioniconsNotificationsOff": true,
    "ioniconsNotificationsOffCircle": true,
    "ioniconsNotificationsOffCircleOutline": true,
    "ioniconsNotificationsOffCircleSharp": true,
    "ioniconsNotificationsOffOutline": true,
    "ioniconsNotificationsOffSharp": true,
    "ioniconsNotificationsOutline": true,
    "ioniconsNotificationsSharp": true,
    "ioniconsNuclear": true,
    "ioniconsNuclearOutline": true,
    "ioniconsNuclearSharp": true,
    "ioniconsNutrition": true,
    "ioniconsNutritionOutline": true,
    "ioniconsNutritionSharp": true,
    "ioniconsOpen": true,
    "ioniconsOpenOutline": true,
    "ioniconsOpenSharp": true,
    "ioniconsOptions": true,
    "ioniconsOptionsOutline": true,
    "ioniconsOptionsSharp": true,
    "ioniconsPaperPlane": true,
    "ioniconsPaperPlaneOutline": true,
    "ioniconsPaperPlaneSharp": true,
    "ioniconsPartlySunny": true,
    "ioniconsPartlySunnyOutline": true,
    "ioniconsPartlySunnySharp": true,
    "ioniconsPause": true,
    "ioniconsPauseCircle": true,
    "ioniconsPauseCircleOutline": true,
    "ioniconsPauseCircleSharp": true,
    "ioniconsPauseOutline": true,
    "ioniconsPauseSharp": true,
    "ioniconsPaw": true,
    "ioniconsPawOutline": true,
    "ioniconsPawSharp": true,
    "ioniconsPencil": true,
    "ioniconsPencilOutline": true,
    "ioniconsPencilSharp": true,
    "ioniconsPeople": true,
    "ioniconsPeopleCircle": true,
    "ioniconsPeopleCircleOutline": true,
    "ioniconsPeopleCircleSharp": true,
    "ioniconsPeopleOutline": true,
    "ioniconsPeopleSharp": true,
    "ioniconsPerson": true,
    "ioniconsPersonAdd": true,
    "ioniconsPersonAddOutline": true,
    "ioniconsPersonAddSharp": true,
    "ioniconsPersonCircle": true,
    "ioniconsPersonCircleOutline": true,
    "ioniconsPersonCircleSharp": true,
    "ioniconsPersonOutline": true,
    "ioniconsPersonRemove": true,
    "ioniconsPersonRemoveOutline": true,
    "ioniconsPersonRemoveSharp": true,
    "ioniconsPersonSharp": true,
    "ioniconsPhoneLandscape": true,
    "ioniconsPhoneLandscapeOutline": true,
    "ioniconsPhoneLandscapeSharp": true,
    "ioniconsPhonePortrait": true,
    "ioniconsPhonePortraitOutline": true,
    "ioniconsPhonePortraitSharp": true,
    "ioniconsPieChart": true,
    "ioniconsPieChartOutline": true,
    "ioniconsPieChartSharp": true,
    "ioniconsPin": true,
    "ioniconsPinOutline": true,
    "ioniconsPinSharp": true,
    "ioniconsPint": true,
    "ioniconsPintOutline": true,
    "ioniconsPintSharp": true,
    "ioniconsPizza": true,
    "ioniconsPizzaOutline": true,
    "ioniconsPizzaSharp": true,
    "ioniconsPlanet": true,
    "ioniconsPlanetOutline": true,
    "ioniconsPlanetSharp": true,
    "ioniconsPlay": true,
    "ioniconsPlayBack": true,
    "ioniconsPlayBackCircle": true,
    "ioniconsPlayBackCircleOutline": true,
    "ioniconsPlayBackCircleSharp": true,
    "ioniconsPlayBackOutline": true,
    "ioniconsPlayBackSharp": true,
    "ioniconsPlayCircle": true,
    "ioniconsPlayCircleOutline": true,
    "ioniconsPlayCircleSharp": true,
    "ioniconsPlayForward": true,
    "ioniconsPlayForwardCircle": true,
    "ioniconsPlayForwardCircleOutline": true,
    "ioniconsPlayForwardCircleSharp": true,
    "ioniconsPlayForwardOutline": true,
    "ioniconsPlayForwardSharp": true,
    "ioniconsPlayOutline": true,
    "ioniconsPlaySharp": true,
    "ioniconsPlaySkipBack": true,
    "ioniconsPlaySkipBackCircle": true,
    "ioniconsPlaySkipBackCircleOutline": true,
    "ioniconsPlaySkipBackCircleSharp": true,
    "ioniconsPlaySkipBackOutline": true,
    "ioniconsPlaySkipBackSharp": true,
    "ioniconsPlaySkipForward": true,
    "ioniconsPlaySkipForwardCircle": true,
    "ioniconsPlaySkipForwardCircleOutline": true,
    "ioniconsPlaySkipForwardCircleSharp": true,
    "ioniconsPlaySkipForwardOutline": true,
    "ioniconsPlaySkipForwardSharp": true,
    "ioniconsPodium": true,
    "ioniconsPodiumOutline": true,
    "ioniconsPodiumSharp": true,
    "ioniconsPower": true,
    "ioniconsPowerOutline": true,
    "ioniconsPowerSharp": true,
    "ioniconsPricetag": true,
    "ioniconsPricetagOutline": true,
    "ioniconsPricetagSharp": true,
    "ioniconsPricetags": true,
    "ioniconsPricetagsOutline": true,
    "ioniconsPricetagsSharp": true,
    "ioniconsPrint": true,
    "ioniconsPrintOutline": true,
    "ioniconsPrintSharp": true,
    "ioniconsPrism": true,
    "ioniconsPrismOutline": true,
    "ioniconsPrismSharp": true,
    "ioniconsPulse": true,
    "ioniconsPulseOutline": true,
    "ioniconsPulseSharp": true,
    "ioniconsPush": true,
    "ioniconsPushOutline": true,
    "ioniconsPushSharp": true,
    "ioniconsQrCode": true,
    "ioniconsQrCodeOutline": true,
    "ioniconsQrCodeSharp": true,
    "ioniconsRadio": true,
    "ioniconsRadioButtonOff": true,
    "ioniconsRadioButtonOffOutline": true,
    "ioniconsRadioButtonOffSharp": true,
    "ioniconsRadioButtonOn": true,
    "ioniconsRadioButtonOnOutline": true,
    "ioniconsRadioButtonOnSharp": true,
    "ioniconsRadioOutline": true,
    "ioniconsRadioSharp": true,
    "ioniconsRainy": true,
    "ioniconsRainyOutline": true,
    "ioniconsRainySharp": true,
    "ioniconsReader": true,
    "ioniconsReaderOutline": true,
    "ioniconsReaderSharp": true,
    "ioniconsReceipt": true,
    "ioniconsReceiptOutline": true,
    "ioniconsReceiptSharp": true,
    "ioniconsRecording": true,
    "ioniconsRecordingOutline": true,
    "ioniconsRecordingSharp": true,
    "ioniconsRefresh": true,
    "ioniconsRefreshCircle": true,
    "ioniconsRefreshCircleOutline": true,
    "ioniconsRefreshCircleSharp": true,
    "ioniconsRefreshOutline": true,
    "ioniconsRefreshSharp": true,
    "ioniconsReload": true,
    "ioniconsReloadCircle": true,
    "ioniconsReloadCircleOutline": true,
    "ioniconsReloadCircleSharp": true,
    "ioniconsReloadOutline": true,
    "ioniconsReloadSharp": true,
    "ioniconsRemove": true,
    "ioniconsRemoveCircle": true,
    "ioniconsRemoveCircleOutline": true,
    "ioniconsRemoveCircleSharp": true,
    "ioniconsRemoveOutline": true,
    "ioniconsRemoveSharp": true,
    "ioniconsReorderFour": true,
    "ioniconsReorderFourOutline": true,
    "ioniconsReorderFourSharp": true,
    "ioniconsReorderThree": true,
    "ioniconsReorderThreeOutline": true,
    "ioniconsReorderThreeSharp": true,
    "ioniconsReorderTwo": true,
    "ioniconsReorderTwoOutline": true,
    "ioniconsReorderTwoSharp": true,
    "ioniconsRepeat": true,
    "ioniconsRepeatOutline": true,
    "ioniconsRepeatSharp": true,
    "ioniconsResize": true,
    "ioniconsResizeOutline": true,
    "ioniconsResizeSharp": true,
    "ioniconsRestaurant": true,
    "ioniconsRestaurantOutline": true,
    "ioniconsRestaurantSharp": true,
    "ioniconsReturnDownBack": true,
    "ioniconsReturnDownBackOutline": true,
    "ioniconsReturnDownBackSharp": true,
    "ioniconsReturnDownForward": true,
    "ioniconsReturnDownForwardOutline": true,
    "ioniconsReturnDownForwardSharp": true,
    "ioniconsReturnUpBack": true,
    "ioniconsReturnUpBackOutline": true,
    "ioniconsReturnUpBackSharp": true,
    "ioniconsReturnUpForward": true,
    "ioniconsReturnUpForwardOutline": true,
    "ioniconsReturnUpForwardSharp": true,
    "ioniconsRibbon": true,
    "ioniconsRibbonOutline": true,
    "ioniconsRibbonSharp": true,
    "ioniconsRocket": true,
    "ioniconsRocketOutline": true,
    "ioniconsRocketSharp": true,
    "ioniconsRose": true,
    "ioniconsRoseOutline": true,
    "ioniconsRoseSharp": true,
    "ioniconsSad": true,
    "ioniconsSadOutline": true,
    "ioniconsSadSharp": true,
    "ioniconsSave": true,
    "ioniconsSaveOutline": true,
    "ioniconsSaveSharp": true,
    "ioniconsScale": true,
    "ioniconsScaleOutline": true,
    "ioniconsScaleSharp": true,
    "ioniconsScan": true,
    "ioniconsScanCircle": true,
    "ioniconsScanCircleOutline": true,
    "ioniconsScanCircleSharp": true,
    "ioniconsScanOutline": true,
    "ioniconsScanSharp": true,
    "ioniconsSchool": true,
    "ioniconsSchoolOutline": true,
    "ioniconsSchoolSharp": true,
    "ioniconsSearch": true,
    "ioniconsSearchCircle": true,
    "ioniconsSearchCircleOutline": true,
    "ioniconsSearchCircleSharp": true,
    "ioniconsSearchOutline": true,
    "ioniconsSearchSharp": true,
    "ioniconsSend": true,
    "ioniconsSendOutline": true,
    "ioniconsSendSharp": true,
    "ioniconsServer": true,
    "ioniconsServerOutline": true,
    "ioniconsServerSharp": true,
    "ioniconsSettings": true,
    "ioniconsSettingsOutline": true,
    "ioniconsSettingsSharp": true,
    "ioniconsShapes": true,
    "ioniconsShapesOutline": true,
    "ioniconsShapesSharp": true,
    "ioniconsShare": true,
    "ioniconsShareOutline": true,
    "ioniconsShareSharp": true,
    "ioniconsShareSocial": true,
    "ioniconsShareSocialOutline": true,
    "ioniconsShareSocialSharp": true,
    "ioniconsShield": true,
    "ioniconsShieldCheckmark": true,
    "ioniconsShieldCheckmarkOutline": true,
    "ioniconsShieldCheckmarkSharp": true,
    "ioniconsShieldHalf": true,
    "ioniconsShieldHalfOutline": true,
    "ioniconsShieldHalfSharp": true,
    "ioniconsShieldOutline": true,
    "ioniconsShieldSharp": true,
    "ioniconsShirt": true,
    "ioniconsShirtOutline": true,
    "ioniconsShirtSharp": true,
    "ioniconsShuffle": true,
    "ioniconsShuffleOutline": true,
    "ioniconsShuffleSharp": true,
    "ioniconsSkull": true,
    "ioniconsSkullOutline": true,
    "ioniconsSkullSharp": true,
    "ioniconsSnow": true,
    "ioniconsSnowOutline": true,
    "ioniconsSnowSharp": true,
    "ioniconsSparkles": true,
    "ioniconsSparklesOutline": true,
    "ioniconsSparklesSharp": true,
    "ioniconsSpeedometer": true,
    "ioniconsSpeedometerOutline": true,
    "ioniconsSpeedometerSharp": true,
    "ioniconsSquare": true,
    "ioniconsSquareOutline": true,
    "ioniconsSquareSharp": true,
    "ioniconsStar": true,
    "ioniconsStarHalf": true,
    "ioniconsStarHalfOutline": true,
    "ioniconsStarHalfSharp": true,
    "ioniconsStarOutline": true,
    "ioniconsStarSharp": true,
    "ioniconsStatsChart": true,
    "ioniconsStatsChartOutline": true,
    "ioniconsStatsChartSharp": true,
    "ioniconsStop": true,
    "ioniconsStopCircle": true,
    "ioniconsStopCircleOutline": true,
    "ioniconsStopCircleSharp": true,
    "ioniconsStopOutline": true,
    "ioniconsStopSharp": true,
    "ioniconsStopwatch": true,
    "ioniconsStopwatchOutline": true,
    "ioniconsStopwatchSharp": true,
    "ioniconsStorefront": true,
    "ioniconsStorefrontOutline": true,
    "ioniconsStorefrontSharp": true,
    "ioniconsSubway": true,
    "ioniconsSubwayOutline": true,
    "ioniconsSubwaySharp": true,
    "ioniconsSunny": true,
    "ioniconsSunnyOutline": true,
    "ioniconsSunnySharp": true,
    "ioniconsSwapHorizontal": true,
    "ioniconsSwapHorizontalOutline": true,
    "ioniconsSwapHorizontalSharp": true,
    "ioniconsSwapVertical": true,
    "ioniconsSwapVerticalOutline": true,
    "ioniconsSwapVerticalSharp": true,
    "ioniconsSync": true,
    "ioniconsSyncCircle": true,
    "ioniconsSyncCircleOutline": true,
    "ioniconsSyncCircleSharp": true,
    "ioniconsSyncOutline": true,
    "ioniconsSyncSharp": true,
    "ioniconsTabletLandscape": true,
    "ioniconsTabletLandscapeOutline": true,
    "ioniconsTabletLandscapeSharp": true,
    "ioniconsTabletPortrait": true,
    "ioniconsTabletPortraitOutline": true,
    "ioniconsTabletPortraitSharp": true,
    "ioniconsTelescope": true,
    "ioniconsTelescopeOutline": true,
    "ioniconsTelescopeSharp": true,
    "ioniconsTennisball": true,
    "ioniconsTennisballOutline": true,
    "ioniconsTennisballSharp": true,
    "ioniconsTerminal": true,
    "ioniconsTerminalOutline": true,
    "ioniconsTerminalSharp": true,
    "ioniconsText": true,
    "ioniconsTextOutline": true,
    "ioniconsTextSharp": true,
    "ioniconsThermometer": true,
    "ioniconsThermometerOutline": true,
    "ioniconsThermometerSharp": true,
    "ioniconsThumbsDown": true,
    "ioniconsThumbsDownOutline": true,
    "ioniconsThumbsDownSharp": true,
    "ioniconsThumbsUp": true,
    "ioniconsThumbsUpOutline": true,
    "ioniconsThumbsUpSharp": true,
    "ioniconsThunderstorm": true,
    "ioniconsThunderstormOutline": true,
    "ioniconsThunderstormSharp": true,
    "ioniconsTicket": true,
    "ioniconsTicketOutline": true,
    "ioniconsTicketSharp": true,
    "ioniconsTime": true,
    "ioniconsTimeOutline": true,
    "ioniconsTimeSharp": true,
    "ioniconsTimer": true,
    "ioniconsTimerOutline": true,
    "ioniconsTimerSharp": true,
    "ioniconsToday": true,
    "ioniconsTodayOutline": true,
    "ioniconsTodaySharp": true,
    "ioniconsToggle": true,
    "ioniconsToggleOutline": true,
    "ioniconsToggleSharp": true,
    "ioniconsTrailSign": true,
    "ioniconsTrailSignOutline": true,
    "ioniconsTrailSignSharp": true,
    "ioniconsTrain": true,
    "ioniconsTrainOutline": true,
    "ioniconsTrainSharp": true,
    "ioniconsTransgender": true,
    "ioniconsTransgenderOutline": true,
    "ioniconsTransgenderSharp": true,
    "ioniconsTrash": true,
    "ioniconsTrashBin": true,
    "ioniconsTrashBinOutline": true,
    "ioniconsTrashBinSharp": true,
    "ioniconsTrashOutline": true,
    "ioniconsTrashSharp": true,
    "ioniconsTrendingDown": true,
    "ioniconsTrendingDownOutline": true,
    "ioniconsTrendingDownSharp": true,
    "ioniconsTrendingUp": true,
    "ioniconsTrendingUpOutline": true,
    "ioniconsTrendingUpSharp": true,
    "ioniconsTriangle": true,
    "ioniconsTriangleOutline": true,
    "ioniconsTriangleSharp": true,
    "ioniconsTrophy": true,
    "ioniconsTrophyOutline": true,
    "ioniconsTrophySharp": true,
    "ioniconsTv": true,
    "ioniconsTvOutline": true,
    "ioniconsTvSharp": true,
    "ioniconsUmbrella": true,
    "ioniconsUmbrellaOutline": true,
    "ioniconsUmbrellaSharp": true,
    "ioniconsUnlink": true,
    "ioniconsUnlinkOutline": true,
    "ioniconsUnlinkSharp": true,
    "ioniconsVideocam": true,
    "ioniconsVideocamOff": true,
    "ioniconsVideocamOffOutline": true,
    "ioniconsVideocamOffSharp": true,
    "ioniconsVideocamOutline": true,
    "ioniconsVideocamSharp": true,
    "ioniconsVolumeHigh": true,
    "ioniconsVolumeHighOutline": true,
    "ioniconsVolumeHighSharp": true,
    "ioniconsVolumeLow": true,
    "ioniconsVolumeLowOutline": true,
    "ioniconsVolumeLowSharp": true,
    "ioniconsVolumeMedium": true,
    "ioniconsVolumeMediumOutline": true,
    "ioniconsVolumeMediumSharp": true,
    "ioniconsVolumeMute": true,
    "ioniconsVolumeMuteOutline": true,
    "ioniconsVolumeMuteSharp": true,
    "ioniconsVolumeOff": true,
    "ioniconsVolumeOffOutline": true,
    "ioniconsVolumeOffSharp": true,
    "ioniconsWalk": true,
    "ioniconsWalkOutline": true,
    "ioniconsWalkSharp": true,
    "ioniconsWallet": true,
    "ioniconsWalletOutline": true,
    "ioniconsWalletSharp": true,
    "ioniconsWarning": true,
    "ioniconsWarningOutline": true,
    "ioniconsWarningSharp": true,
    "ioniconsWatch": true,
    "ioniconsWatchOutline": true,
    "ioniconsWatchSharp": true,
    "ioniconsWater": true,
    "ioniconsWaterOutline": true,
    "ioniconsWaterSharp": true,
    "ioniconsWifi": true,
    "ioniconsWifiOutline": true,
    "ioniconsWifiSharp": true,
    "ioniconsWine": true,
    "ioniconsWineOutline": true,
    "ioniconsWineSharp": true,
    "ioniconsWoman": true,
    "ioniconsWomanOutline": true,
    "ioniconsWomanSharp": true,
    "iosTransitionAnimation": true,
    "isNuxtError": true,
    "isPlatform": true,
    "isPrerendered": true,
    "isProxy": true,
    "isReactive": true,
    "isReadonly": true,
    "isRef": true,
    "isShallow": true,
    "isVue2": true,
    "isVue3": true,
    "loadPayload": true,
    "loadingController": true,
    "markRaw": true,
    "mdTransitionAnimation": true,
    "menuController": true,
    "mergeModels": true,
    "modalController": true,
    "navigateTo": true,
    "nextTick": true,
    "onActivated": true,
    "onBeforeMount": true,
    "onBeforeRouteLeave": true,
    "onBeforeRouteUpdate": true,
    "onBeforeUnmount": true,
    "onBeforeUpdate": true,
    "onDeactivated": true,
    "onErrorCaptured": true,
    "onIonViewDidEnter": true,
    "onIonViewDidLeave": true,
    "onIonViewWillEnter": true,
    "onIonViewWillLeave": true,
    "onMounted": true,
    "onNuxtReady": true,
    "onPrehydrate": true,
    "onRenderTracked": true,
    "onRenderTriggered": true,
    "onScopeDispose": true,
    "onServerPrefetch": true,
    "onUnmounted": true,
    "onUpdated": true,
    "openURL": true,
    "pickerController": true,
    "popoverController": true,
    "prefetchComponents": true,
    "preloadComponents": true,
    "preloadPayload": true,
    "preloadRouteComponents": true,
    "prerenderRoutes": true,
    "provide": true,
    "proxyRefs": true,
    "reactive": true,
    "readonly": true,
    "ref": true,
    "refreshCookie": true,
    "refreshNuxtData": true,
    "reloadNuxtApp": true,
    "requestIdleCallback": true,
    "resolveComponent": true,
    "setInterval": true,
    "setPageLayout": true,
    "setResponseStatus": true,
    "shallowReactive": true,
    "shallowReadonly": true,
    "shallowRef": true,
    "showError": true,
    "toRaw": true,
    "toRef": true,
    "toRefs": true,
    "toValue": true,
    "toastController": true,
    "triggerRef": true,
    "tryUseNuxtApp": true,
    "unref": true,
    "updateAppConfig": true,
    "useAppConfig": true,
    "useAsyncData": true,
    "useAttrs": true,
    "useBackButton": true,
    "useCookie": true,
    "useCssModule": true,
    "useCssVars": true,
    "useError": true,
    "useFetch": true,
    "useHead": true,
    "useHeadSafe": true,
    "useHydration": true,
    "useId": true,
    "useIonRouter": true,
    "useKeyboard": true,
    "useLazyAsyncData": true,
    "useLazyFetch": true,
    "useLoadingIndicator": true,
    "useModel": true,
    "useNuxtApp": true,
    "useNuxtData": true,
    "usePreviewMode": true,
    "useRequestEvent": true,
    "useRequestFetch": true,
    "useRequestHeader": true,
    "useRequestHeaders": true,
    "useRequestURL": true,
    "useRoute": true,
    "useRouteAnnouncer": true,
    "useRouter": true,
    "useRuntimeConfig": true,
    "useScript": true,
    "useScriptClarity": true,
    "useScriptCloudflareWebAnalytics": true,
    "useScriptCrisp": true,
    "useScriptEventPage": true,
    "useScriptFathomAnalytics": true,
    "useScriptGoogleAdsense": true,
    "useScriptGoogleAnalytics": true,
    "useScriptGoogleMaps": true,
    "useScriptGoogleTagManager": true,
    "useScriptHotjar": true,
    "useScriptIntercom": true,
    "useScriptLemonSqueezy": true,
    "useScriptMatomoAnalytics": true,
    "useScriptMetaPixel": true,
    "useScriptNpm": true,
    "useScriptPlausibleAnalytics": true,
    "useScriptSegment": true,
    "useScriptStripe": true,
    "useScriptTriggerConsent": true,
    "useScriptTriggerElement": true,
    "useScriptVimeoPlayer": true,
    "useScriptXPixel": true,
    "useScriptYouTubePlayer": true,
    "useSeoMeta": true,
    "useServerHead": true,
    "useServerHeadSafe": true,
    "useServerSeoMeta": true,
    "useShadowRoot": true,
    "useSlots": true,
    "useState": true,
    "useTemplateRef": true,
    "useTransitionState": true,
    "watch": true,
    "watchEffect": true,
    "watchPostEffect": true,
    "watchSyncEffect": true,
    "withCtx": true,
    "withDirectives": true,
    "withKeys": true,
    "withMemo": true,
    "withModifiers": true,
    "withScopeId": true
  }
}